{
    "configurations": [
        {
            "name": "Win64",
            "defines": [
                "_DEBUG",
                "UNICODE",
                "_UNICODE"
            ],
            "compilerPath": "C:/msys64/mingw64/bin/g++.exe",
            "intelliSenseMode": "gcc-x64",
            "browse": {
                "path": [
                    "${workspaceFolder}"
                ],
                "limitSymbolsToIncludedHeaders": true,
                "databaseFilename": ""
            },
            "includePath": [
                "${default}"
            ],
            "configurationProvider": "ms-vscode.makefile-tools"
        }
    ],
    "version": 4
}